{"name":"3rd International Conference on Communication and Electronics Systems","series":"","short":"","website":"http://icoecs.org","content":"3rd International Conference on Communication and Electronics Systems (ICCES 2018) is being organized on 15-16 October 2018\\. ICCES will provide an outstanding international forum for sharing knowledge and results in all fields of Engineering and Technology. ICCES provides quality key experts who provide an opportunity in bringing up innovative ideas. Recent updates in the in the field of technology will be a platform for the upcoming researchers. The conference will be Complete, Concise, Clear and Cohesive in terms of research related to Communication and Electronics systems.","date_start":"2018-10-15","date_end":"2018-10-16","important_dates":{"abstract":"","full":"2018-08-15","notification":"","final":""},"topics":["Engineering & Technology","Computer/Informatics","Database Management Systems"],"location":{"virtual":"","full":["Coimbatore","India"],"name":"","street":"","city":"Coimbatore","state":"","ZIP":"","country":"India"},"organizers":["PPG Institute of Technology"],"societies":[],"indexes":[],"emails":[]}