{"name":"GSTF QQE - 7th Annual International Conference on Qualitative and Quantitative Economics Research","series":"","short":"","website":"http://qq-economics.org","content":"The Qualitative and Quantitative Economics Research Conference aims at presenting a platform to the researchers, academia, business leaders, policy makers and the students to explore innovative ways of finding solutions to various economic problems through qualitative and quantitative research techniques. These techniques have become indispensable in dealing with various economic issues, be it forecasting future growth of countries, estimating capital inflows and outflows, taking the pulse of stock markets or fearing exchange rate jitters to the economies. The policy makers and business leaders do make their decisions based on well researched propositions. The world economy is going through a rough path of growth and stability though US has shown better growth and Europe also improving, but China going down has raised new issues and problems. All the economies aim at sustainable growth and prosperity. It is very relevant to explore into these issues.","date_start":"2017-06-05","date_end":"2017-06-06","important_dates":{"abstract":"","full":"2017-03-31","notification":"","final":""},"topics":["Business","Economics","Economics & econometrics"],"location":{"virtual":"","full":["Singapore","Singapore"],"name":"","street":"","city":"Singapore","state":"","ZIP":"","country":"Singapore"},"organizers":["Global Science and Technology Forum"],"societies":[],"indexes":[],"emails":[]}