{"name":"Resilient Computing Platforms and Technologies for Disaster Management","series":"","short":"","website":"https://www.lsbu.ac.uk/conferences/rescue-2017","content":"CALL FOR PAPERS\\_RESCUE-2017 The aim of this international workshop , in line with the 10th IEEE International Conference on Cyber, Physical and Social Computing, is to provide a forum for the researchers, operators, and government administrators to share the latest technical development, good practice and experience learned from dealing with disasters. Topics to be covered in this special session include, but are not limited to: a) 5G technology for disaster management b) Mobile Edge Computing / Fog Computing for disaster management c) Software Defined networking for disaster management d) Location and tracking based services for disaster management e) Ad hoc and multi-hop wireless networks for disaster monitoring and communications f) Internet of Things (IoT) for disaster monitoring and management g) Cloud computing for disaster management h) Applications of smartphones and apps for disaster management i) Satellite communications for disaster management j) Unmanned Aerial Vehicles (UAVs) for disaster management k) Robotics for disaster management l) Human Computer Interaction for disaster management m) Practice and experience from disaster management n) Government policies for disaster management o) Standardisation for disaster management Submission Deadline: 31/03/2017 (extended)","date_start":"2017-06-21","date_end":"2017-06-23","important_dates":{"abstract":"","full":"2017-03-31","notification":"","final":""},"topics":["Engineering & Technology","Computer/Informatics"],"location":{"virtual":"","full":["United Kingdom"],"name":"","street":"","city":"","state":"","ZIP":"","country":""},"organizers":[""],"societies":[],"indexes":[],"emails":[]}