{"name":"Developing Research Skills","series":"","short":"","website":"https://www.lcir.co.uk/research-skills-workshop","content":"The workshop is designed for students, young scholars and independent researchers who would like to improve their academic research skills in order to succeed in studies and in career. Flexible and interactive, this workshop will provide an overview of research, including how to find information, generate the aims of a project, read critically, evaluate sources, and manage a research project. This workshop offers delegates the opportunity to explore interdisciplinary research and critical thinking. Topics will include: Interdisciplinarity and Critical Thinking: Awareness and looking at the overlaps within disciplines Critiquing the literature (quoting, paraphrasing and summarising) How to get started (exploring literature and locating emerging themes) The workshop will be divided into 2 sessions with a short break. All the participants will receive certificates of attendance. In order to book a place, please register on https://registration.lcir.co.uk Registration fee – 45 GBP","date_start":"2021-04-18","date_end":"","important_dates":{"abstract":"","full":"","notification":"","final":""},"topics":["Education / Legal / Other","Other","Sociology, Social Sciences"],"location":{"virtual":"","full":["Online Event","United Kingdom"],"name":"","street":"","city":"Online Event","state":"","ZIP":"","country":"United Kingdom"},"organizers":["London Centre for Interdisciplinary Research and Academic LAB"],"societies":[],"indexes":[],"emails":[]}