{"name":"Sustainable Alternative Materials and Bio-Based Materials Summit, March 30-31 2022","series":"","short":"","website":"https://go.evvnt.com/972287-2?pid=4868","content":"The race is on to bioengineer carbon-neutral, recyclable, biodegradable, and affordable materials, with a growing number of mainstream brands committing to integrating sustainable materials into their product lines, establishing new relationships with bio-based material innovators leading to commercial growth within the sustainable goods sector. With next-generation bio-based alternatives reputed as the new frontier for sustainable materials, the 2nd Annual Sustainable Alternative and Bio-Based Materials Summit will showcase original technological advances and innovations powering the new wave of alternative materials, shaping a more sustainable fashion industry. Whether you have an innovative bio-based material or technology or are looking to integrate more sustainable and bio-based textiles into your apparel product lines, this virtual event will equip you with the information and partnerships to succeed. URLs: Tickets: https://go.evvnt.com/972287-0?pid=4868 Brochure: https://go.evvnt.com/972287-3?pid=4868 Prices: General admission: USD 2099.0, Vendor admission: USD 2998.0, Academic and Start-ups: USD 1899.0 Speakers: Enrica Arena Co-Founder - Orange Fiber, Isaac Emery Founder - Informed Sustainability Consulting, Shahriare Mahmood Director of Sustainability - Spinnova Ltd, Jessica Kruger Founder - LUXTRA, Robert Nicoll Co-Founder and CMO - Chip\\[s\\] Board, Kenji Higashi Head of Business Development and Sustainability - Spiber, Andras Forgacs Co-Founder and Chief Executive Officer - Modern Meadow, Dr Amy Congdon Head of Design Intelligence - Biofabricate, Irene Maffini Sustainability Investor - Sustainable Accelerator, Aaron Nesser Co-founder and CEO - AlgiKnit, Aniela Hoitink Founder, Research Design and Development - MycoTEX, Ingvar Helgason Co-founder and Chief Executive Officer - VitroLabs, Alissa Baier-Lentz Co-Founder - Kintra Fibres, Yotam Solomon Creative Director - Covalent Fashion, Sydney Gladman Chief Scientific Officer - Material Innovation Initiative, Dr Raquel Prado Head of Research and Sustainability - Ananas Anam, Jordi BeneytoFerre Senior Manager of Global Innovation - Icebreaker, Stefano Babbini Founder and CEO - MOGU, Maurizio Montalti Co-Founder - MOGU, Edward Brial Co-Founder - Materra, Katina Boutis Director of Sustainability - Everlane, Carolyn Swenson Senior Materials Manager - Reformation, Billy McCall Co-Founder - Kintra Fibers, Luke Haverhals Founder and CEO - Natural Fiber Welding, Charlotte Borst Innovation Associate - Fashion for Good, Meg Montes Head of Systems and Business Operations - Ananas Anam, Michiel van Deursen Founder - Capital V Time: 08:00 - 17:00","date_start":"2022-03-30","date_end":"2022-03-31","important_dates":{"abstract":"","full":"","notification":"","final":""},"topics":["Education / Legal / Other","Education"],"location":{"virtual":"","full":["Online Event",""],"name":"","street":"","city":"Online Event","state":"","ZIP":"","country":""},"organizers":["Hanson Wade"],"societies":[],"indexes":[],"emails":[]}