{"name":"18th International Conference on Metabolomics and Proteomics","series":"","short":"","website":"https://metabolomics.metabolomicsconference.com","content":"Metabolomics 2021 is the premier event that brings together a unique and international mix of experts, researchers and decision makers both from academia and industry across the globe to exchange their knowledge, expertise and research innovations to build a world-class plant genomics conference.","date_start":"2021-12-01","date_end":"2021-12-02","important_dates":{"abstract":"","full":"","notification":"","final":""},"topics":["Education / Legal / Other","Other"],"location":{"virtual":"","full":["Online Event","Anguilla"],"name":"","street":"","city":"Online Event","state":"","ZIP":"","country":"Anguilla"},"organizers":[""],"societies":[],"indexes":[],"emails":[]}