{"name":"2021 IEEE 6th International Conference on Big Data Analytics","series":"","short":"ICBDA 2021","website":"http://www.icbda.org","content":"Publication: IEEE Conference proceeding. All accepted conference papers will be submitted for inclusion into IEEE Xplore, EI compendex and Scopus Database.","date_start":"2021-03-05","date_end":"2021-03-08","important_dates":{"abstract":"","full":"2021-02-01","notification":"","final":""},"topics":["Engineering & Technology","Computer/Informatics","Big Data Mining & Analysis"],"location":{"virtual":"","full":["Xiamen","China"],"name":"","street":"","city":"Xiamen","state":"","ZIP":"","country":"China"},"organizers":[""],"societies":[],"indexes":[],"emails":[]}