{"name":"2021 International Conference on Materials Science and Chemistry Engineering","series":"","short":"ICMSCE 2021","website":"www.ic-msce.net","content":"2021 International Conference on Materials Science and Chemistry Engineering (ICMSCE 2021) will be held in Qingdao, China during May 26-28, 2021\\. It brings together leading academic scientists, researchers and research scholars to exchange and share their experiences and research results on all aspects of materials science and engineering (IC-MSE 2021). Prof. Nuno Dinis Corticos from Universidade de Lisboa, Portugal, and Prof. Masaru Tanaka from Institute of?Materials Chemistry?and?Engineering, Kyushu?University, Japan will give keynote speach. All the registered and presented papers will be published in the volume of IOP- Materials Science and Engineering (MSE): Conference Series, which will be submitted to EI Compendex, Scopus, Thomson Reuters (WoS), Inspec, and other databases for review and indexing. Submission Deadline Before May 5, 2021 Notification of Acceptance On May 15, 2021 Registration Deadline Before May 20, 2021 Conference Dates On May 26-28, 2021 Paper submission: 1.Conference Submission System: https://cmt3.research.microsoft.com/ICMSCE2021 2.Mail: icmsce@isaeri.org Conference Secretary: Ms. Alice Li Tell: +852-30756685 Mail: icmsce@isaeri.org Conference website: www.ic-msce.net","date_start":"2021-05-26","date_end":"2021-05-28","important_dates":{"abstract":"","full":"2021-05-05","notification":"","final":""},"topics":["Engineering & Technology","Chemical"],"location":{"virtual":"","full":["Qingdao","China"],"name":"","street":"","city":"Qingdao","state":"","ZIP":"","country":"China"},"organizers":["Shandong University, China"],"societies":[],"indexes":[],"emails":["icmsce@isaeri.org"]}