{"name":"34th World Conference on Applied Science, Engineering and Technology","series":"","short":"","website":"https://wcaset.com/dubai","content":"IFERP Organizes 34th World Conference on Applied science, Engineering and Technology which will be held in Dubai, UAE on 23rd – 24th March, 2021 at 9:00 AM to 6:00 PM. WCASET is the leading academic and Industry gathering for presenting novel and fundamental advances in the field of Applied science, Engineering and Technology. WCASET aim to reach every nook and corner of the world to bring in talented individuals and to provide them a platform to showcase their findings. WCASET is built on the confidence and constant support of its Advisory Board which represents different background, culture, diversity but with a sole aim of bring a revolution in generating solutions for the current challenges with a multidisciplinary approach and within the next 5 years with the continuous help and support from people all across the world, we dream of becoming the next biggest brand of multidisciplinary conferences in the Asia Pacific Region and then conquer the world of multidisciplinary approach for the betterment of mankind.","date_start":"2021-03-23","date_end":"2021-03-24","important_dates":{"abstract":"","full":"2021-02-01","notification":"","final":""},"topics":["Engineering & Technology","Other","Engineering Science & Technology"],"location":{"virtual":"","full":["Dubai","United Arab Emirates"],"name":"","street":"","city":"Dubai","state":"","ZIP":"","country":"United Arab Emirates"},"organizers":["Institute For Engineering Research And Publications (IFERP)"],"societies":[],"indexes":[],"emails":[]}