{"name":"2022 6th International Conference on Robotics and Automation Sciences","series":"","short":"ICRAS 2022","website":"http://www.icras.org","content":"Publication: All submitted papers must be written in English. Accepted papers will be published in ICRAS 2022 Conference Proceedings, which will be published and submitted to IEEE Xplore. Those papers will be indexed by Ei Compendex, Scopus and other main academical databases.","date_start":"2022-06-09","date_end":"2022-06-11","important_dates":{"abstract":"","full":"2022-04-25","notification":"","final":""},"topics":["Engineering & Technology","Computer/Informatics","Automation Science"],"location":{"virtual":"","full":["Wuhan","China"],"name":"","street":"","city":"Wuhan","state":"","ZIP":"","country":"China"},"organizers":[""],"societies":[],"indexes":[],"emails":[]}