{"name":"Business Continuity Auditing Plans Using ISO 22301","series":"","short":"","website":"https://www.complianceonline.com/iso-22301-business-continuity-auditing-plans-seminar-training-80545SEM-prdsm?channel=brownwalker","content":"This seminar will cover the best practices for implementing and auditing a Business Continuity Plan. The speaker will discuss the lifecycle of a BCP program with specific emphasis on Risk Assessment and Business Impact Analysis, Designing a living BCP & Testing & Maintenance. The program will also detail the various standards from FFIEC to ISO. Participants will understand what’s involved in a full BCP program and have insights based upon field experience that can be applied to Internal Audit work and BCP. The session will provide you with tools that you can bring back to your company to improve upon BCP programs & ability to audit them to provide targeted recommendations.","date_start":"2020-09-10","date_end":"2020-09-11","important_dates":{"abstract":"","full":"","notification":"","final":""},"topics":["Business","Management / Leadership","Risk Management"],"location":{"virtual":"","full":["Online Event",""],"name":"","street":"","city":"Online Event","state":"","ZIP":"","country":""},"organizers":["Compliance Online"],"societies":[],"indexes":[],"emails":[]}