{"name":"2021 6th International Conference on Advances on Clean Energy Research（ICACER 2021）","series":"","short":"","website":"http://www.icacer.com","content":"Publication: After a careful reviewing process, accepted, registered and presented papers will be published in the ICACER 2021 Conference Proceedings in Energy Reports (ISSN: 2352-4847) Indexed by Science Citation Index Expanded Ei Compendex & Scopus Directory of Open Access Journals (DOAJ).","date_start":"2021-04-15","date_end":"2021-04-17","important_dates":{"abstract":"","full":"2021-03-01","notification":"","final":""},"topics":["Engineering & Technology","Renewable Energy/Nuclear","Energy, clean, renewable"],"location":{"virtual":"","full":["Barcelona","Spain"],"name":"","street":"","city":"Barcelona","state":"","ZIP":"","country":"Spain"},"organizers":[""],"societies":[],"indexes":[],"emails":[]}