{"name":"2021 3rd International Conference on Environment Sciences and Renewable Energy","series":"","short":"ESRE 2021","website":"http://www.esre.org","content":"Publication & Index： All accepted papers of ESRE 2021 will be published in International Conference Proceedings which is indexed by EI Compendex, Scopus, Thomson Reuters (WoS), Inspec,et al.","date_start":"2021-05-21","date_end":"2021-05-24","important_dates":{"abstract":"","full":"2021-04-01","notification":"","final":""},"topics":["Engineering & Technology","Renewable Energy/Nuclear","environmental engineering"],"location":{"virtual":"","full":["Chengdu","China"],"name":"","street":"","city":"Chengdu","state":"","ZIP":"","country":"China"},"organizers":[""],"societies":[],"indexes":[],"emails":[]}