{"name":"2023 International Conference on Ubiquitous Communication (Ucom 2023)","series":"","short":"","website":"http://ucom.org.cn","content":"Publication: The accepted papers passed through the peer-reviewed process after proper registration and presentation will be published into conference proceedings by IEEE, which will be included into IEEE Xplore and indexed by EI compendex and Scopus.","date_start":"2023-07-07","date_end":"2023-07-09","important_dates":{"abstract":"","full":"2023-05-20","notification":"","final":""},"topics":["Engineering & Technology","Computer/Informatics","communication engineering"],"location":{"virtual":"","full":["Xi'an","China"],"name":"","street":"","city":"Xi'an","state":"","ZIP":"","country":"China"},"organizers":[""],"societies":[],"indexes":[],"emails":[]}