{"name":"6th World Congress on Disaster Management","series":"","short":"","website":"www.wcdm.co.in","content":"The 6th WCDM will be organized jointly by Government of Uttarakhand, Disaster Management Initiatives and Convergence Society (DMICS), Hyderabad, Uttarakhand State Disaster Management Authority (USDMA) and Uttarakhand State Council for Science & Technology (UCOST), Dehradun. Besides several academic and research institutions would join as knowledge partners. Building on the experiences gained in the preceding Congresses, the 6th WCDM would involve national, provincial, and local governments, scientific and technical organizations, academia, professional bodies, industry, civil society, practitioners, and media from around the world, besides UN bodies and multilateral and regional organizations. The 6th WCDM would provide a platform for sharing critical understanding, research, innovation, and good practices on disaster risk reduction and promoting interaction among scientists, policymakers, and practitioners, besides forging new partnerships and networks for building resilience to disasters. The 6th WCDM has been designed to be the largest assembly on disaster management outside the UN system.","date_start":"2023-11-28","date_end":"2023-12-01","important_dates":{"abstract":"","full":"2023-10-15","notification":"","final":""},"topics":["Social Sciences","Other"],"location":{"virtual":"","full":["Dehradun","India"],"name":"","street":"","city":"Dehradun","state":"","ZIP":"","country":"India"},"organizers":["Government of Uttarakhand, DMICS, USDMA and UCOST"],"societies":[],"indexes":[],"emails":[]}