{"name":"2023 International Conference on Image Processing and Artificial Intelligence","series":"","short":"IPAI 2023","website":"http://www.ipai.org","content":"Publication: Submitted paper will be peer reviewed by conference committees, and accepted papers will be recommended to be published into IPAI 2023 conference proceedings.","date_start":"2023-03-29","date_end":"2023-03-31","important_dates":{"abstract":"","full":"2023-02-20","notification":"","final":""},"topics":["Engineering & Technology","Computer/Informatics","Image Processing"],"location":{"virtual":"","full":["Prague","Czech Republic"],"name":"","street":"","city":"Prague","state":"","ZIP":"","country":"Czech Republic"},"organizers":[""],"societies":[],"indexes":[],"emails":[]}