{"name":"6th International Conference on Research in Education","series":"","short":"","website":"https://www.icreconf.org","content":"The 6th International Conference on Research in Education, 03-05 March 2023 in Vienna, Austria aims to bring together academia, researchers, and scholars to exchange information and share experiences and research results about all aspects of specialized and interdisciplinary fields. This event provides an opportunity for all to network, share ideas and present their research to a worldwide community. Discussion on the latest innovations, trends and practical concerns, and challenges faced in these fields are also encouraged. We are delighted to announce that the education conference 2023 has established a great and friendly community of multinational researchers who are fond of sharing their common experiences In this regard, the scientific and executive committees of the Conference kindly invite all professors, researchers, and executive officials to submit, individually or in partnership with other researchers, their valuable articles comprising the latest scientific and research findings on the main or related themes and topics of the international conference on education to the Conference Secretariat.","date_start":"2023-03-03","date_end":"2023-03-05","important_dates":{"abstract":"","full":"2023-02-10","notification":"","final":""},"topics":["Education / Legal / Other","Education","Education, teaching"],"location":{"virtual":"","full":["Viena","Austria"],"name":"","street":"","city":"Viena","state":"","ZIP":"","country":"Austria"},"organizers":["Acavent"],"societies":[],"indexes":[],"emails":[]}