{"name":"2nd International Conference On Human Genetics and Genetical Disorders","series":"","short":"","website":"https://geneticsresearch.net","content":"Human Genetics and Genetical Disorders-2025 extend our immense pleasure and honor to invite you to attend the 2nd International Conference on Human Genetics and Genetical Disorders which is scheduled on April 14-16, 2024 in Paris, France. One of these directions was the need for genetic studies to identify genes and genetic markers of diagnostic, prognostic and therapeutic value Genetic processes work in combination with an organism's environment and experiences to influence development and behavior often referred to as nature versus nurture.","date_start":"2025-04-14","date_end":"2025-04-16","important_dates":{"abstract":"","full":"2025-03-05","notification":"","final":""},"topics":["Medicine & Health","Other","Plant Biology And Genetics","Genomics"],"location":{"virtual":"","full":["Paris","paris France"],"name":"","street":"","city":"Paris","state":"","ZIP":"","country":"paris France"},"organizers":["FOSTER RESEARCH"],"societies":[],"indexes":[],"emails":[]}