{"name":"4th World Conference on Foreign Language Education","series":"","short":"","website":"https://www.worldfle.org","content":"The 4th World Conference on Foreign Language Education is premiering in one of the most multicultural cities in the world – London, UK. This is the perfect backdrop to discussing such important subjects in the field as language teaching, discourse analysis, translational studies, psycholinguistics, language terminology, and emotional and cognitive aspects of foreign language learning, among others.","date_start":"2025-07-16","date_end":"2025-07-18","important_dates":{"abstract":"","full":"2025-06-27","notification":"","final":""},"topics":["Education / Legal / Other","Education","Languages (Human)"],"location":{"virtual":"","full":["London","United Kingdom"],"name":"","street":"","city":"London","state":"","ZIP":"","country":"United Kingdom"},"organizers":["Proud Pen"],"societies":[],"indexes":[],"emails":[]}