{"name":"ILL 2024 | Innovation in Language Learning 17th Edition - International Conference","series":"","short":"","website":"https://go.evvnt.com/2213676-0?pid=4868","content":"The 17th Edition of the International Conference Innovation in Language Learning will take place online on 6 November 2024 and in Florence (Italy) on 7 - 8 November 2024\\. The event brings together teachers, researchers, practitioners and project managers from all over the world to share findings, expertise and experience about innovative language teaching and learning methodologies. Important dates: - 26 September 2024: abstracts submission deadline - 25 September 2024: papers submission deadline (possibility to extend) - 6 November 2024: Conference day of the ONLINE EVENT - 7/8 November 2024: Conference days of the ONSITE EVENT IN FLORENCE (ITALY) Onsite participants are welcome in Florence for two full days of thought-provoking sessions, integrated by endless networking opportunities and social events. Online participants can contribute with asynchronous or synchronous online presentations. The latter will be delivered on 6 November via the Conference Virtual Platform. During the Conference: - All accepted papers will be presented onsite and online. - Questions and Answers sessions will follow each paper presentation. - Poster presentation sessions will be held onsite and online. - Networking opportunities will be organized. All accepted papers will be included in the Conference Proceedings published with ISBN, ISSN and DOI codes. The publication will be sent to be reviewed for inclusion in the Conference Proceedings Citation Index by ISI-Clarivate- Web of Science and SCOPUS. The publication will also be included in Academia.edu and indexed in Google Scholar. Contact: conference@pixel-online.net Official website: https://conference.pixel-online.net/ICT4LL/callforpapers.php Video: https://youtu.be/iFeLD-zpc1s URL: Tickets: https://go.evvnt.com/2213676-2?pid=4868 Time: 9:00 AM - 6:00 PM Venue details: FH55 Grand Hotel Mediterraneo, 44 Lungarno del Tempio, Firenze, Toscana, 50121, Italy Price: General Admission: EUR 250.00","date_start":"2024-11-07","date_end":"2024-11-08","important_dates":{"abstract":"","full":"2024-09-26","notification":"","final":""},"topics":["Education / Legal / Other","Education","Education","Higher Education"],"location":{"virtual":"","full":["Firenze","Toscana Italy"],"name":"","street":"","city":"Firenze","state":"","ZIP":"","country":"Toscana Italy"},"organizers":["Pixel International Conferences"],"societies":[],"indexes":[],"emails":["conference@pixel-online.net"]}