{"name":"2025 International Conference on Marketing and Behavioral Science","series":"","short":"ICMBS 2025","website":"https://www.icmbs.org","content":"Publication: Submissions will be reviewed by the conference committees and editorial board, and Accepted and presented papers will be published into ICMBS 2025 conference proceedings, which will be submitted to Scopus for indexing.","date_start":"2025-07-15","date_end":"2025-07-17","important_dates":{"abstract":"","full":"2025-06-01","notification":"","final":""},"topics":["Business","Marketing/Social-Networking","Marketing & Advertising"],"location":{"virtual":"","full":["Fukuoka","Japan"],"name":"","street":"","city":"Fukuoka","state":"","ZIP":"","country":"Japan"},"organizers":["ICMBS 2025"],"societies":[],"indexes":[],"emails":[]}