{"name":"2024 the 14th International Conference on Power and Energy Systems","series":"","short":"ICPES 2024","website":"http://icpes.org","content":"Publication: Accepted papers will be published into conference proceedings by IEEE, which will be included in IEEE Xplore, indexed by Ei Compendex and Scopus after the conference. \\* The conference proceedings of previous conferences have been published by IEEE, indexed by Scopus & EI Compendex successfully.","date_start":"2024-12-13","date_end":"2024-12-16","important_dates":{"abstract":"","full":"2024-11-01","notification":"","final":""},"topics":["Engineering & Technology","Renewable Energy/Nuclear","Energy Engineering","Power Electronics & Control"],"location":{"virtual":"","full":["Chengdu","China"],"name":"","street":"","city":"Chengdu","state":"","ZIP":"","country":"China"},"organizers":["Southwest Jiaotong University, UESTC, PES, IEEE"],"societies":[],"indexes":[],"emails":[]}